LICENSE
MANIFEST.in
README.rst
requirements.txt
setup.py
sentinel5dl/__init__.py
sentinel5dl/__main__.py
sentinel5dl.egg-info/PKG-INFO
sentinel5dl.egg-info/SOURCES.txt
sentinel5dl.egg-info/dependency_links.txt
sentinel5dl.egg-info/entry_points.txt
sentinel5dl.egg-info/requires.txt
sentinel5dl.egg-info/top_level.txt
tests/__init__.py
tests/__main__.py
tests/test_lib.py