Metadata-Version: 2.1
Name: sentinel5dl
Version: 1.0
Summary: Sentinel-5p Downloader
Home-page: https://github.com/emissions-api/sentinel5dl
Author: Emissions API Developers
License: MIT
Platform: UNKNOWN
Classifier: Development Status :: 4 - Beta
Classifier: Intended Audience :: Developers
Classifier: License :: OSI Approved :: MIT License
Classifier: Programming Language :: Python :: 3
Classifier: Programming Language :: Python :: 3.6
Classifier: Programming Language :: Python :: 3.7
Classifier: Programming Language :: Python :: 3.8
Classifier: Operating System :: OS Independent
Classifier: Topic :: Scientific/Engineering :: GIS
